orlo/__init__.py
orlo/__main__.py
orlo/_version.py
orlo/app.py
orlo/config.py
orlo/error_handlers.py
orlo/exceptions.py
orlo/orm.py
orlo/queries.py
orlo/stats.py
orlo/user_auth.py
orlo/util.py
orlo/migrations/0868747e62ff_add_unique_constraints.py
orlo/migrations/a8cdfffc29a3_fix_release_notes.pyc
orlo/migrations/e60a77e44da8_initial_db_revision.py
orlo/migrations/e60a77e44da8_initial_db_revision.pyc
orlo/migrations/script.py.mako
orlo/routes/__init__.py
orlo/routes/base.py
orlo/routes/import_.py
orlo/routes/info.py
orlo/routes/internal.py
orlo/routes/packages.py
orlo/routes/releases.py
orlo/routes/stats.py
orlo-0.4.3.dist-info/DESCRIPTION.rst
orlo-0.4.3.dist-info/METADATA
orlo-0.4.3.dist-info/RECORD
orlo-0.4.3.dist-info/WHEEL
orlo-0.4.3.dist-info/entry_points.txt
orlo-0.4.3.dist-info/metadata.json
orlo-0.4.3.dist-info/top_level.txt
