Metadata-Version: 2.0
Name: orlo
Version: 0.4.3
Summary: Deployment data capture API
Home-page: https://github.com/eBayClassifiedsGroup/orlo
Author: Alex Forbes
Author-email: alforbes@ebay.com
License: GPL
Platform: UNKNOWN
Requires-Dist: Flask (>=0.12)
Requires-Dist: Flask-Alembic (>=2.0.1)
Requires-Dist: Flask-HTTPAuth
Requires-Dist: Flask-Migrate
Requires-Dist: Flask-SQLAlchemy
Requires-Dist: Flask-Script (>=2.0.5)
Requires-Dist: Flask-TokenAuth
Requires-Dist: arrow
Requires-Dist: gunicorn
Requires-Dist: orloclient (>=0.4.5)
Requires-Dist: psycopg2
Requires-Dist: pyldap
Requires-Dist: pytz
Requires-Dist: sqlalchemy-utils
Provides-Extra: doc
Requires-Dist: Flask (>=0.12); extra == 'doc'
Requires-Dist: Flask-Alembic (>=2.0.1); extra == 'doc'
Requires-Dist: Flask-HTTPAuth; extra == 'doc'
Requires-Dist: Flask-Migrate; extra == 'doc'
Requires-Dist: Flask-SQLAlchemy; extra == 'doc'
Requires-Dist: Flask-Script (>=2.0.5); extra == 'doc'
Requires-Dist: Flask-TokenAuth; extra == 'doc'
Requires-Dist: arrow; extra == 'doc'
Requires-Dist: orloclient (>=0.2.0); extra == 'doc'
Requires-Dist: pytz; extra == 'doc'
Requires-Dist: sphinxcontrib-httpdomain; extra == 'doc'
Requires-Dist: sqlalchemy-utils; extra == 'doc'
Provides-Extra: install
Requires-Dist: Flask (>=0.12); extra == 'install'
Requires-Dist: Flask-Alembic (>=2.0.1); extra == 'install'
Requires-Dist: Flask-HTTPAuth; extra == 'install'
Requires-Dist: Flask-Migrate; extra == 'install'
Requires-Dist: Flask-SQLAlchemy; extra == 'install'
Requires-Dist: Flask-Script (>=2.0.5); extra == 'install'
Requires-Dist: Flask-TokenAuth; extra == 'install'
Requires-Dist: arrow; extra == 'install'
Requires-Dist: gunicorn; extra == 'install'
Requires-Dist: orloclient (>=0.4.5); extra == 'install'
Requires-Dist: psycopg2; extra == 'install'
Requires-Dist: pyldap; extra == 'install'
Requires-Dist: pytz; extra == 'install'
Requires-Dist: sqlalchemy-utils; extra == 'install'
Provides-Extra: test
Requires-Dist: Flask (>=0.12); extra == 'test'
Requires-Dist: Flask-Alembic (>=2.0.1); extra == 'test'
Requires-Dist: Flask-HTTPAuth; extra == 'test'
Requires-Dist: Flask-Migrate; extra == 'test'
Requires-Dist: Flask-SQLAlchemy; extra == 'test'
Requires-Dist: Flask-Script (>=2.0.5); extra == 'test'
Requires-Dist: Flask-Testing; extra == 'test'
Requires-Dist: Flask-TokenAuth; extra == 'test'
Requires-Dist: arrow; extra == 'test'
Requires-Dist: gunicorn; extra == 'test'
Requires-Dist: mockldap; extra == 'test'
Requires-Dist: orloclient (>=0.4.0); extra == 'test'
Requires-Dist: orloclient (>=0.4.5); extra == 'test'
Requires-Dist: psycopg2; extra == 'test'
Requires-Dist: pyldap; extra == 'test'
Requires-Dist: pytest; extra == 'test'
Requires-Dist: pytz; extra == 'test'
Requires-Dist: sqlalchemy-utils; extra == 'test'
Requires-Dist: tox; extra == 'test'
